<?xml version="1.0" encoding="utf-8" ?>
<dwsync>
<file name="application.js" server="outerplex.com//outerplex/_apps/needGod/" local="130566966631801848" remote="130566894600000000" Dst="2" />
<file name="fastclick.js" server="outerplex.com//outerplex/_apps/needGod/" local="130566966631841851" remote="130566894600000000" Dst="2" />
<file name="jquery-2.0.3.min.js" server="outerplex.com//outerplex/_apps/needGod/" local="130566966632331879" remote="130566894600000000" Dst="2" />
<file name="jquery.mobile-1.2.0.min.js" server="outerplex.com//outerplex/_apps/needGod/" local="130566966632501888" remote="130566894600000000" Dst="2" />
<file name="mobileinit.js" server="outerplex.com//outerplex/_apps/needGod/" local="130566966632541891" remote="130566894600000000" Dst="2" />
<file name="jquery-1.7.2.min.js" server="outerplex.com//outerplex/_apps/needGod/" local="130566966632021861" remote="130566894600000000" Dst="2" />
<file name="jquery-migrate-1.2.1.min.js" server="outerplex.com//outerplex/_apps/needGod/" local="130566972381300701" remote="130566900600000000" Dst="2" />
<file name="jquery-1.11.0.min.js" server="outerplex.com//outerplex/_apps/needGod/" local="130566972303556254" remote="130566900600000000" Dst="2" />
</dwsync>